lambert_rs/__init__.py
lambert_rs/lambert_rs.abi3.so
lambert_rs-0.0.17.dist-info/METADATA
lambert_rs-0.0.17.dist-info/WHEEL
lambert_rs-0.0.17.dist-info/RECORD
