Metadata-Version: 2.4
Name: lambert-rs
Version: 0.0.17
Classifier: Programming Language :: Rust
Classifier: Programming Language :: Python :: Implementation :: CPython
Classifier: Programming Language :: Python :: Implementation :: PyPy
Classifier: Programming Language :: Python :: 3
Classifier: Programming Language :: Python :: 3.8
Classifier: Programming Language :: Python :: 3.9
Classifier: Programming Language :: Python :: 3.10
Classifier: Programming Language :: Python :: 3.11
Classifier: Programming Language :: Python :: 3.12
Classifier: Programming Language :: Python :: 3.13
Classifier: Development Status :: 4 - Beta
Classifier: Intended Audience :: Science/Research
Classifier: Topic :: Scientific/Engineering :: Physics
Summary: Rust + PyO3 implementation of the Izzo Lambert solver
Keywords: lambert,orbital-mechanics,astrodynamics,rust
Author-email: Your Name <your.email@example.com>
License: MIT
Requires-Python: >=3.8
Project-URL: Documentation, https://github.com/yourusername/lambert_rust#readme
Project-URL: Homepage, https://github.com/yourusername/lambert_rust
Project-URL: Repository, https://github.com/yourusername/lambert_rust
